imagescript/__init__.py
imagescript/_utils.py
imagescript/cmd.py
imagescript/converter.py
ImageScript-1.1.0.dist-info/LICENSE.txt
ImageScript-1.1.0.dist-info/METADATA
ImageScript-1.1.0.dist-info/WHEEL
ImageScript-1.1.0.dist-info/entry_points.txt
ImageScript-1.1.0.dist-info/top_level.txt
ImageScript-1.1.0.dist-info/RECORD
