Metadata-Version: 2.1
Name: ImageScript
Version: 1.1.0
Summary: A python library and command line tool to convert text to images and back.
Author-email: Nikolas Teuschl <niklas.teuschl@hotmail.com>
License: Copyright 2024 Nikolas Teuschl
Project-URL: Homepage, https://github.com/NeoSecundus/ImageScript
Project-URL: Source, https://github.com/NeoSecundus/ImageScript
Keywords: steganography,image,security,storage,encryption,experimental
Classifier: Programming Language :: Python :: 3
Classifier: License :: OSI Approved :: MIT License
Classifier: Operating System :: OS Independent
Requires-Python: >=3.12
License-File: LICENSE.txt
Requires-Dist: pillow >=11.0.0
Requires-Dist: argparse >=1.4.0
Requires-Dist: pycryptodome >=3.21.0
Requires-Dist: numpy >=2.1.3
Provides-Extra: dev
Requires-Dist: ruff >=0.7.3 ; extra == 'dev'
Requires-Dist: pyright >=1.1.388 ; extra == 'dev'
Requires-Dist: pdoc >=15.0.0 ; extra == 'dev'
Requires-Dist: build >=1.2.2.post1 ; extra == 'dev'
Requires-Dist: twine >=5.1.1 ; extra == 'dev'
